{
  "translation": {
    "shared": {
      "loading": "Loading...",
      "cancel": "Cancel",
      "save": "Save",
      "add": "Add",
      "remove": "Remove",
      "yes": "Yes",
      "no": "No",
      "close": "Close",
      "delete": "Delete",
      "defaultApplicationName": "ToDo"
    },
    "settingsDialog": {
      "title": "Settings",
      "columnHeading": "Manage Columns",
      "newColumn": "New Column",
      "general": "General",
      "columns": "Columns",
      "language": "Language",
      "stats": "Stats",
      "statsChart": {
        "startDateLabel": "Start Date",
        "chartTitle": "To-Do List Activity Chart",
        "datasets": {
          "added": "Tasks Added",
          "completed": "Tasks Completed"
        }
      },
      "languagePreference": "Select your preferred language from the dropdown above."
    },
    "task": {
      "comments": {
        "pascal": "Comments",
        "camel": "comments"
      },
      "name": "Task Name",
      "description": "Description",
      "deleteTitle": "Delete Task",
      "deleteDescription": "Are you sure you want to delete this task? This action cannot be undone.",
      "editTitle": "Edit Task",
      "addComment": "Add a comment",
      "blur": "Blur Tasks",
      "show": "Show Tasks"
    },
    "column": {
      "newTask": "New Task",
      "add": "Add",
      "completed": "Completed",
      "deleteTitle": "Delete Column",
      "deleteDescription": "Are you sure you want to delete this column? All tasks within this column will also be deleted.",
      "hide": "HIDE",
      "show": "SHOW",
      "taskCount": "This column has {{tasks}} tasks.",
      "noColumns": "No columns yet, get started by clicking the add button.",
      "name": "Enter a name for this column.",
      "edit": "Edit"
    },
    "emptyState": {
      "title": "Welcome to the To-Do App!",
      "getStarted": "Click the settings icon in the top right to get started by adding columns.",
      "or": "OR",
      "explore": "Explore the",
      "github": "GitHub repository"
    },
    "share": {
      "title": "Share Your Data",
      "description": "You can share your tasks by sending the link below. When someone opens the link, they'll be able to view your tasks exactly as you see them.",
      "notice": "Please note that any changes made by the person opening the link will only apply to their own view, and will not affect your tasks. Likewise, any changes you make will not be reflected in the shared link.",
      "shareableUrl": "Shareable URL",
      "copy": "Click the copy icon to copy the URL.",
      "importTitle": "Import Data from URL",
      "importDescription": "We found data in the URL. Would you like to import it and overwrite your current tasks?"
    },
    "dialogs": {
      "logout": {
        "title": "Log Out Confirmation",
        "description": "Are you sure you want to log out?"
      }
    },
    "auth": {
      "loading": "Loading, please wait.",
      "title": "Secure Login",
      "description": "To access your account, we use a secure single sign-on platform that ensures a seamless and safe login experience.",
      "redirectMsg": "You will be securely redirected to <strong>{{domain}}</strong> to complete your login process.",
      "continue": "Continue to Login"
    }
  }
}
